Workbook
Name aporte: APP!$D$17
Name invertimento_usado: APP!$D$20
Name investimento_usado: APP!$D$20
Name patrimonio: APP!$D$21
Name qtd_anos: APP!$D$18
Name rendimento_carteira: APP!$D$12
Name sugestao_investimento: APP!$D$13
Name taxa_mesnsal: APP!$D$19

Sheet APP
B10: CONFIGURAÇÕES
B11: Salário | D11: 10000
B12: Rendimento de Carteira | D12: 0.006
B13: Sugestão de Investimento (30%) | D13: =D11*30% -> 3000
B14: Modo de Investimento | D14: 30% do Salário
B16: INVESTIMENTO MENSAL
B17: Quanto invertir po mês? | D17: 500
B18: Por quantos anos? | D18: 5
B19: Taxa de rendimento mensal? | D19: 0.01079
B20: Investimento usado | D20: =IF(D14="30% do Salário",sugestao_investimento,aporte) -> 3000
B21: Patrimônio acumulado? | D21: =FV(taxa_mesnsal,qtd_anos*12,aporte*-1) -> 41888.457
B22: Dividendos Mensais? | D22: =patrimonio*rendimento_carteira -> 251.33074
B24: CENÁRIOS | C24: Patrimônio | D24: Dividendo
A25: 2 | B25: Quanto em 2 anos? | C25: =FV($D$19,$A25*12,$D$17*-1) -> 13613.814 | D25: =C25*rendimento_carteira -> 81.682882
A26: 5 | B26: Quanto em 5 anos? | C26: =FV($D$19,$A26*12,$D$17*-1) -> 41888.457 | D26: =C26*rendimento_carteira -> 251.33074
A27: 10 | B27: Quanto em 10 anos? | C27: =FV($D$19,$A27*12,$D$17*-1) -> 121642.11 | D27: =C27*rendimento_carteira -> 729.85264
A28: 20 | B28: Quanto em 20 anos? | C28: =FV($D$19,$A28*12,$D$17*-1) -> 562599.2 | D28: =C28*rendimento_carteira -> 3375.5952
A29: 30 | B29: Quanto em 30 anos? | C29: =FV($D$19,$A29*12,$D$17*-1) -> 2161084.8 | D29: =C29*rendimento_carteira -> 12966.509
B34: PERFIL | C34: CONSERVADOR
B35: VALOR A SER INVESTIDO POR MÊS | C35: =invertimento_usado -> 3000
B37: TIPO DE FII | C37: Percentual Sugerido | D37: Valores
B38: PAPEL | C38: =VLOOKUP($C$34&"-"&B38,Apoio!$A:$D,4,FALSE) -> 0.3 | D38: =$C$35*C38 -> 900
B39: TIJOLO | C39: =VLOOKUP($C$34&"-"&B39,Apoio!$A:$D,4,FALSE) -> 0.5 | D39: =$C$35*C39 -> 1500
B40: HÍBRIDOS | C40: =VLOOKUP($C$34&"-"&B40,Apoio!$A:$D,4,FALSE) -> 0.1 | D40: =$C$35*C40 -> 300
B41: FOfs | C41: =VLOOKUP($C$34&"-"&B41,Apoio!$A:$D,4,FALSE) -> 0.1 | D41: =$C$35*C41 -> 300
B42: DESENVOLVIMENTO | C42: =VLOOKUP($C$34&"-"&B42,Apoio!$A:$D,4,FALSE) -> 0 | D42: =$C$35*C42 -> 0
B43: HOTELARIAS | C43: =VLOOKUP($C$34&"-"&B43,Apoio!$A:$D,4,FALSE) -> 0 | D43: =$C$35*C43 -> 0
D44: =SUM(D38:D43) -> 3000

Sheet Apoio
A2: CHAVE | B2: PERFIL | C2: TIPO DE FII | D2: %
A3: =B3&"-"&C3 -> Conservador-PAPEL | B3: Conservador | C3: PAPEL | D3: 0.3 | H3: %
A4: =B4&"-"&C4 -> Conservador-TIJOLO | B4: Conservador | C4: TIJOLO | D4: 0.5 | G4: Moderado-TIJOLO | H4: =VLOOKUP(G4,$A:$D,4,FALSE) -> 0.35
A5: =B5&"-"&C5 -> Conservador-HÍBRIDOS | B5: Conservador | C5: HÍBRIDOS | D5: 0.1
A6: =B6&"-"&C6 -> Conservador-FOfs | B6: Conservador | C6: FOfs | D6: 0.1
A7: =B7&"-"&C7 -> Conservador-DESENVOLVIMENTO | B7: Conservador | C7: DESENVOLVIMENTO | D7: 0
A8: =B8&"-"&C8 -> Conservador-HOTELARIAS | B8: Conservador | C8: HOTELARIAS | D8: 0
A9: =B9&"-"&C9 -> Moderado-PAPEL | B9: Moderado | C9: PAPEL | D9: 0.32
A10: =B10&"-"&C10 -> Moderado-TIJOLO | B10: Moderado | C10: TIJOLO | D10: 0.35
A11: =B11&"-"&C11 -> Moderado-HÍBRIDOS | B11: Moderado | C11: HÍBRIDOS | D11: 0.08
A12: =B12&"-"&C12 -> Moderado-FOfs | B12: Moderado | C12: FOfs | D12: 0.05
A13: =B13&"-"&C13 -> Moderado-DESENVOLVIMENTO | B13: Moderado | C13: DESENVOLVIMENTO | D13: 0.1
A14: =B14&"-"&C14 -> Moderado-HOTELARIAS | B14: Moderado | C14: HOTELARIAS | D14: 0.1
A15: =B15&"-"&C15 -> Agressivo-PAPEL | B15: Agressivo | C15: PAPEL | D15: 0.5
A16: =B16&"-"&C16 -> Agressivo-TIJOLO | B16: Agressivo | C16: TIJOLO | D16: 0.1
... A20: =B20&"-"&C20 -> Agressivo-HOTELARIAS | B20: Agressivo | C20: HOTELARIAS | D20: 0.1
